{
  "13-24m": [
    "cognition",
    "fine_motor",
    "gross_motor",
    "language_comprehension",
    "language_expression",
    "social_emotional"
  ],
  "2-6m": [
    "gross_motor"
  ],
  "25-36m": [
    "cognition",
    "fine_motor",
    "gross_motor",
    "language_comprehension",
    "language_expression",
    "social_emotional"
  ],
  "37-48m": [
    "cognition",
    "fine_motor",
    "gross_motor",
    "language_comprehension",
    "language_expression",
    "social_emotional"
  ],
  "49-60m": [
    "cognition",
    "fine_motor",
    "gross_motor",
    "language_comprehension",
    "language_expression",
    "social_emotional"
  ],
  "61-72m": [
    "cognition",
    "fine_motor",
    "gross_motor",
    "language_comprehension",
    "language_expression",
    "social_emotional"
  ],
  "7-12m": [
    "fine_motor",
    "gross_motor",
    "language_comprehension",
    "social_emotional"
  ]
}
